fixpoint_openapi/__init__.py
fixpoint_openapi/api/__init__.py
fixpoint_openapi/api/fixpoint_api.py
fixpoint_openapi/api_client.py
fixpoint_openapi/api_response.py
fixpoint_openapi/configuration.py
fixpoint_openapi/exceptions.py
fixpoint_openapi/models/__init__.py
fixpoint_openapi/models/app_log_level_type.py
fixpoint_openapi/models/fixpoint_batch_delete_dataset_logs_request.py
fixpoint_openapi/models/fixpoint_create_open_ai_chat_input_log_request.py
fixpoint_openapi/models/fixpoint_create_open_ai_chat_output_log_request.py
fixpoint_openapi/models/fixpoint_post_dataset_logs_request.py
fixpoint_openapi/models/fixpoint_update_spending_totals_request.py
fixpoint_openapi/models/fixpointv1_model.py
fixpoint_openapi/models/fixpointv1_spend_cap.py
fixpoint_openapi/models/protobuf_any.py
fixpoint_openapi/models/protobuf_null_value.py
fixpoint_openapi/models/routing_block_ab.py
fixpoint_openapi/models/rpc_status.py
fixpoint_openapi/models/tool_call_function.py
fixpoint_openapi/models/v1_ab_chat_completion.py
fixpoint_openapi/models/v1_api_secret.py
fixpoint_openapi/models/v1_api_secret_provider.py
fixpoint_openapi/models/v1_app_log.py
fixpoint_openapi/models/v1_attribute_filters.py
fixpoint_openapi/models/v1_batch_create_fine_tune_jobs_request.py
fixpoint_openapi/models/v1_batch_create_fine_tune_jobs_response.py
fixpoint_openapi/models/v1_chat_completion.py
fixpoint_openapi/models/v1_chat_completion_choice.py
fixpoint_openapi/models/v1_chat_completion_usage.py
fixpoint_openapi/models/v1_create_ab_chat_completion_request.py
fixpoint_openapi/models/v1_create_api_secret_request.py
fixpoint_openapi/models/v1_create_app_logs_request.py
fixpoint_openapi/models/v1_create_app_logs_response.py
fixpoint_openapi/models/v1_create_dataset_request.py
fixpoint_openapi/models/v1_create_dataset_response.py
fixpoint_openapi/models/v1_create_likes_request.py
fixpoint_openapi/models/v1_create_likes_response.py
fixpoint_openapi/models/v1_create_log_attribute_request.py
fixpoint_openapi-0.4.0.dist-info/LICENSE
fixpoint_openapi-0.4.0.dist-info/METADATA
fixpoint_openapi-0.4.0.dist-info/WHEEL
fixpoint_openapi-0.4.0.dist-info/RECORD
