Metadata-Version: 2.1
Name: fixpoint_openapi
Version: 0.4.0
Summary: OpenAPI client for Fixpoint - Auto-improvement to make your LLM apps smarter
Home-page: https://github.com/gofixpoint/python-openapi-client
License: License :: OSI Approved :: Apache Software License
Keywords: OpenAPI,OpenAPI-Generator
Author: Fixpoint
Author-email: team@fixpoint.co
Requires-Python: >=3.8,<4.0
Classifier: License :: OSI Approved :: Apache Software License
Classifier: License :: Other/Proprietary License
Classifier: Programming Language :: Python :: 3
Classifier: Programming Language :: Python :: 3.8
Classifier: Programming Language :: Python :: 3.9
Classifier: Programming Language :: Python :: 3.10
Classifier: Programming Language :: Python :: 3.11
Classifier: Programming Language :: Python :: 3.12
Requires-Dist: pydantic (>=2)
Requires-Dist: python-dateutil (>=2.8.2)
Requires-Dist: typing-extensions (>=4.7.1)
Requires-Dist: urllib3 (>=1.25.3)
Project-URL: Repository, https://github.com/gofixpoint/python-openapi-client
